README.txt
setup.py
1pass.egg-info/PKG-INFO
1pass.egg-info/SOURCES.txt
1pass.egg-info/dependency_links.txt
1pass.egg-info/requires.txt
1pass.egg-info/top_level.txt
bin/1pass
onepassword/__init__.py
onepassword/cli.py
onepassword/encryption_key.py
onepassword/keychain.py