Metadata-Version: 1.0
Name: 1pass
Version: 0.2.0
Summary: A Python library and command line interface for 1Password
Home-page: http://github.com/georgebrock/1pass
Author: George Brocklehurst
Author-email: george@georgebrock.com
License: MIT
Platform: UNKNOWN
